mlClustering/__init__.py
mlClustering/utils.py
mlClustering/clustering/__init__.py
mlClustering/composition/__init__.py
mlClustering/composition/self_tuning.py
mlClustering/metrics/__init__.py
mlClustering/metrics/clustering_indicators.py
mlClustering-0.0.2.dist-info/LICENSE
mlClustering-0.0.2.dist-info/METADATA
mlClustering-0.0.2.dist-info/WHEEL
mlClustering-0.0.2.dist-info/top_level.txt
mlClustering-0.0.2.dist-info/RECORD
